{"name":"Cassandra.Confluvium M | Slow Milsim Test-And-Eval 8+4","map":"Market","password":false,"raw":{"protocol":17,"folder":"sandstorm","game":"Insurgency: Sandstorm","appId":581320,"numplayers":0,"numbots":0,"listentype":"d","environment":"l","secure":1,"version":"1.1.0.0","steamid":"85568392924554201","tags":["V:174497","S:523","MatchServer_b:false","ModList_s:1120893","851078","391659","371483","180266","94277","Mutators_s:DinghyLoadout"],"rules":{"Coop_b":"true","CustomRules_b":"false","Day_b":"true","GameMode_s":"Checkpoint","MatchServer_b":"false","ModList_s":"1120893,851078,391659,371483,180266,94277","Mods_b":"true","Mutated_b":"true","Mutators_s":"DinghyLoadout","Night_b":"false","OfficialRuleset_b":"false","PlrC_i":"5","PlrM_i":"8","Pwd_b":"false","RankedServer_b":"true","S":"523","Versus_b":"false"}},"maxplayers":8,"players":[],"bots":[],"connect":"144.202.3.182:27102","ping":89,"updated_at":1634780632059}
